openrgb/__init__.py
openrgb/network.py
openrgb/orgb.py
openrgb/utils.py
openrgb/plugins/__init__.py
openrgb/plugins/common.py
openrgb/plugins/effects.py
openrgb_python_ng-0.3.3.dist-info/LICENSE.md
openrgb_python_ng-0.3.3.dist-info/METADATA
openrgb_python_ng-0.3.3.dist-info/WHEEL
openrgb_python_ng-0.3.3.dist-info/top_level.txt
openrgb_python_ng-0.3.3.dist-info/RECORD
