Metadata-Version: 2.1
Name: openrgb-python-ng
Version: 0.3.3
Summary: A python client for the OpenRGB SDK
Home-page: https://github.com/Emiliopg91/openrgb-python
Author: epulidogil
Classifier: Programming Language :: Python :: 3
Classifier: License :: OSI Approved :: GNU General Public License v3 (GPLv3)
Classifier: Operating System :: OS Independent
Requires-Python: >=3.7
License-File: LICENSE.md
